MANIFEST.in
README.txt
setup.py
docs/HISTORY.txt
src/zeam/__init__.py
src/zeam.form.plone.egg-info/PKG-INFO
src/zeam.form.plone.egg-info/SOURCES.txt
src/zeam.form.plone.egg-info/dependency_links.txt
src/zeam.form.plone.egg-info/namespace_packages.txt
src/zeam.form.plone.egg-info/not-zip-safe
src/zeam.form.plone.egg-info/requires.txt
src/zeam.form.plone.egg-info/top_level.txt
src/zeam/form/__init__.py
src/zeam/form/plone/__init__.py
src/zeam/form/plone/configure.zcml
src/zeam/form/plone/form.py
src/zeam/form/plone/meta.py
src/zeam/form/plone/widgets.py
src/zeam/form/plone/form_templates/formtemplate.pt
src/zeam/form/plone/i18n/zeam-form-plone.pot
src/zeam/form/plone/i18n/en/LC_MESSAGES/zeam-form-plone.mo
src/zeam/form/plone/i18n/en/LC_MESSAGES/zeam-form-plone.po
src/zeam/form/plone/i18n/nl/LC_MESSAGES/zeam-form-plone.mo
src/zeam/form/plone/i18n/nl/LC_MESSAGES/zeam-form-plone.po
src/zeam/form/plone/profiles/default/cssregistry.xml
src/zeam/form/plone/profiles/default/jsregistry.xml
src/zeam/form/plone/resources/arrow_down.png
src/zeam/form/plone/resources/arrow_left.png
src/zeam/form/plone/resources/arrow_right.png
src/zeam/form/plone/resources/arrow_up.png
src/zeam/form/plone/resources/json-template.js
src/zeam/form/plone/resources/widgets.css
src/zeam/form/plone/resources/widgets.js
src/zeam/form/plone/widgets_templates/plonemultiselectfieldwidget.pt
src/zeam/form/plone/widgets_templates/plonewysiwygfieldwidget.pt