Metadata-Version: 1.0
Name: zeam.form.plone
Version: 1.0
Summary: Plone integration for Zeam Form
Home-page: http://pypi.python.org/pypi/zeam.form.plone
Author: Sylvain Viollon
Author-email: thefunny@gmail.com
License: BSD
Keywords: grok form framework plone
Platform: UNKNOWN
Classifier: Framework :: Zope2
Classifier: Framework :: Plone
Classifier: License :: OSI Approved :: BSD License
Classifier: Programming Language :: Python
Classifier: Topic :: Software Development :: Libraries :: Python Modules
